geodisasters/__init__.py
geodisasters/services.py
geodisasters-0.1.1.dist-info/LICENSE
geodisasters-0.1.1.dist-info/METADATA
geodisasters-0.1.1.dist-info/WHEEL
geodisasters-0.1.1.dist-info/top_level.txt
geodisasters-0.1.1.dist-info/RECORD
